# 20231011

## [03｜工作台：JVM运行时数据区的内部机制是怎样的？](https://time.geekbang.org/column/article/690294)

Java 虚拟机栈在 Java 运行时内存里占据着重要的地位，主要用来支持 Java 程序的运行。在一个 Java 程序中，每一个线程的运行都对应着一个虚拟机栈。

### 动态链接（Dynamic Linking）

动态链接会在程序运行时通过链接到运行时常量池的引用，来找到与每个栈帧相关的方法。这让我们在实现方法调用的时候能够进行动态链接。

#### 主要作用

1. 决定方法如何调用
2. 提高性能

### 返回地址

无论是正常退出还是异常退出，方法的返回地址都很关键，可以帮助程序恢复并继续执行。对于正常退出，返回地址一般来自 PC 计数器；对于异常退出，则来自异常处理器表。

### 本地方法栈

本地方法栈与虚拟机栈在功能上有很多相似之处，但是它们之间还是有一些区别的。虚拟机栈主要用于执行 Java 方法，也就是字节码，而本地方法栈主要负责执行由非 Java 语言（如 C、C++）编写的 Native 方法。

和虚拟机栈一样，本地方法栈也可能在栈深度超过虚拟机允许的范围时，抛出 StackOverflowError，在虚拟机栈动态扩展无法申请到足够内存时，抛出 OutOfMemoryError。本地方法栈不仅关系到 Java 与其他语言的互通，而且对程序性能也有很大影响。随着 JDK 不断发展，本地方法栈也在逐步优化。

### 重点回顾

这节课我们学习了 JVM 运行时数据区的内部构成和应用场景。其中，虚拟机栈是 JVM 方法执行内存模型的载体，程序计数器则是将 JVM 中的线程与底层硬件平台线程平滑切换的关键组件。局部变量表通过槽位共用的方式提高了内存效率，同时动态链接也是提高 Java 程序性能的重要手段。通过学习这些内容，我们更深入地理解了 JVM 运行时数据区的实现原理和优化策略。所以我们要尽可能地减小每个变量的作用域，为虚拟机提供了更多的可能性去优化局部变量表，重用槽位，从而减少了内存占用。知己知彼，百战不殆，越熟悉每天陪伴我们的工具，越有利于我们写出更优雅的 Java 程序。希望你学完这节课的内容之后，再去检查下自己写的代码，看看还有哪些可优化的空间。

## code

``` java
public class OperandStack{
    public static void main(String[] args) {
        int result = add(1, 2);
        System.out.println(result);
    }
 
    public static int add(int a, int b) {
        int c = a + b;
        return c;
    }
}
```

`javap -c OperandStack`

``` java
public class OperandStack {
    public static void main(java.lang.String[]);
    Code:
       0: iconst_1
       1: iconst_2
       2: invokestatic  #2 // Method add:(II)I
       5: istore_1
       6: getstatic     #3 // Field java/lang/System.out:Ljava/io/PrintStream;
       9: iload_1
      10: invokevirtual #4 // Method java/io/PrintStream.println:(I)V
      13: return
 
    public static int add(int, int);
    Code:
       0: iload_0
       1: iload_1
       2: iadd
       3: istore_2
       4: iload_2
       5: ireturn
}
```
对于 add 方法，字节码的工作方式是这样的：iload_0 和 iload_1 把参数 a、b 分别压入操作数栈。iadd 指令弹出栈顶的两个元素，也就是参数 a 和 b，执行加法操作，并把结果变量 c 压回栈顶。将栈顶元素保存到局部变量表的第二个位置，也就是变量 c 所在的位置，是 istore_2 的操作。iload_2 的工作是把局部变量表中第二个位置的元素，也就是变量 c 的值，重新放回栈顶。ireturn 是把栈顶元素（变量 c 的值）作为返回值返回。


``` java
public class DynamicLinking {
    public void methodA(){
        System.out.println("---------start methodA-------------");
    }
}
```

``` bash
javac DynamicLinking.java
javap -verbose -p DynamicLinking
```

``` java
public void methodA();
        
  descriptor: ()V
  flags: ACC_PUBLIC
  Code:
   stack=2, locals=1, args_size=1
   0: getstatic     #3    //使用动态链接，指向Field out:Ljava/io/PrintStream;
   3: ldc           #4    //使用动态链接，引用String "---------start methodA-------------"
   5: invokevirtual #5    
  LineNumberTable:
   line 7: 0
   line 8: 8
  LocalVariableTable:
    Start  Length  Slot  Name   Signature
    0       9     0  this   Lcom/future/DynamicLinking; 
```

## comment

### Levi

老师请教一个问题，Slot只保存局部变量的值吗，比如a=2，slot中保存的是2这个数据值，那a这个变量被保存在哪里呢？

作者回复: 在JVM中，Slot（插槽）是用来存储局部变量的数据结构。当一个方法被调用时，JVM会在栈帧中为这个方法分配一个局部变量表，以存放该方法的所有局部变量。而每一个局部变量，在这个局部变量表中就占用一个或者多个Slot。所以，对于你提到的情况，变量a的值2会被保存在Slot中，而变量a本身，也就是变量名，不会存储在Slot中。在Java中，变量名只是在编译阶段存在，用来帮助开发者理解和操作数据。一旦编译结束，变量名就不再需要了，因为JVM在运行时，只关心数据，而不关心这个数据是通过什么变量名得到的。所以说，变量a本身会在编译结束后被丢弃，只有它的值2会被保存在Slot中。

## 固定片尾

此文章为10月Day4学习笔记，内容来源于极客时间《云时代的 JVM 原理与实战》，强烈推荐该课程！/推荐该课程